MANIFEST.in
setup.cfg
setup.py
pygci/__init__.py
pygci/api.py
pygci/endpoints.py
pygci/exceptions.py
pygci/helpers.py
pygci.egg-info/PKG-INFO
pygci.egg-info/SOURCES.txt
pygci.egg-info/dependency_links.txt
pygci.egg-info/requires.txt
pygci.egg-info/top_level.txt