Metadata-Version: 1.0
Name: pygci
Version: 0.1
Summary: Simple Python wrapper for the Google Civic Information API
Home-page: https://github.com/aleccunningham/pygci/tree/master
Author: Alec Cunningham
Author-email: aleccunningham96@gmail.com
License: MIT License
